setup.cfg
setup.py
flask_auth_utils/__init__.py
flask_auth_utils/auth_blueprint.py
flask_auth_utils/forms.py
flask_auth_utils/initialize_authentication.py
flask_auth_utils/models.py
flask_auth_utils/user_service.py
flask_auth_utils/utils.py
flask_auth_utils.egg-info/PKG-INFO
flask_auth_utils.egg-info/SOURCES.txt
flask_auth_utils.egg-info/dependency_links.txt
flask_auth_utils.egg-info/requires.txt
flask_auth_utils.egg-info/top_level.txt